pydread.cpython-37m-darwin.so
pydread-0.0b9.dist-info/LICENSE.txt
pydread-0.0b9.dist-info/METADATA
pydread-0.0b9.dist-info/WHEEL
pydread-0.0b9.dist-info/top_level.txt
pydread-0.0b9.dist-info/RECORD
